pytest_extended_mock/__init__.py
pytest_extended_mock/plugin.py
pytest_extended_mock-0.1.2.dist-info/METADATA
pytest_extended_mock-0.1.2.dist-info/WHEEL
pytest_extended_mock-0.1.2.dist-info/entry_points.txt
pytest_extended_mock-0.1.2.dist-info/RECORD
