Metadata-Version: 2.3
Name: pytest-extended-mock
Version: 0.1.2
Summary: a pytest extension for easy mock setup
License: MIT
Author: Adam Davenport
Requires-Python: >=3.12
Classifier: Framework :: Pytest
Classifier: Programming Language :: Python
Classifier: Topic :: Software Development :: Testing
Requires-Dist: pytest (>=8.3.5,<9.0.0)
Requires-Dist: pytest-mock (>=3.14.0,<4.0.0)
Project-URL: Homepage, https://github.com/adam006/pytest-mock-setup
Project-URL: Repository, https://github.com/adam006/pytest-mock-setup
